ilua/__init__.py
ilua/_unixfifo.py
ilua/_win32namedpipe.py
ilua/app.py
ilua/appbase.py
ilua/builtins.lua
ilua/connection.py
ilua/consoleapp.py
ilua/history.py
ilua/inspector.py
ilua/interp.lua
ilua/kernel.py
ilua/kernelbase.py
ilua/message.py
ilua/namedpipe.py
ilua/proto.py
ilua/sockets.py
ilua/version.py
ilua/ext/inspect.lua
ilua/ext/json.lua
ilua/ext/netstring.lua
ilua-0.2.1.data/data/share/jupyter/kernels/lua/kernel.json
ilua-0.2.1.data/data/share/jupyter/kernels/lua/logo-32x32.png
ilua-0.2.1.data/data/share/jupyter/kernels/lua/logo-64x64.png
ilua-0.2.1.data/data/share/jupyter/kernels/lua/logo-license.txt
ilua-0.2.1.dist-info/LICENSE
ilua-0.2.1.dist-info/METADATA
ilua-0.2.1.dist-info/WHEEL
ilua-0.2.1.dist-info/entry_points.txt
ilua-0.2.1.dist-info/top_level.txt
ilua-0.2.1.dist-info/RECORD
