Metadata-Version: 2.1
Name: ilua
Version: 0.2.1
Summary: Portable Lua kernel for Jupyter
Home-page: https://github.com/guysv/ilua
Author: Guy Sviry
Author-email: sviryguy@gmail.com
License: GPLv2
Keywords: lua interactive console jupyter kernel
Platform: UNKNOWN
Classifier: Development Status :: 3 - Alpha
Classifier: Intended Audience :: Developers
Classifier: Topic :: Software Development :: Interpreters
Classifier: License :: OSI Approved :: GNU General Public License v2 (GPLv2)
Classifier: Operating System :: OS Independent
Classifier: Programming Language :: Python :: 2
Classifier: Programming Language :: Python :: 2.7
Classifier: Programming Language :: Python :: 3
Classifier: Programming Language :: Python :: 3.4
Classifier: Programming Language :: Python :: 3.5
Classifier: Programming Language :: Python :: 3.6
Classifier: Programming Language :: Python :: 3.7
Requires-Dist: twisted
Requires-Dist: termcolor
Requires-Dist: pygments
Requires-Dist: txzmq
Requires-Dist: jupyter-core
Requires-Dist: jupyter-console
Requires-Dist: pywin32 ; sys_platform == "win32"
